hi_hamsunwoo/__init__.py
hi_hamsunwoo/hello.py
hi_hamsunwoo-0.8.0.dist-info/METADATA
hi_hamsunwoo-0.8.0.dist-info/WHEEL
hi_hamsunwoo-0.8.0.dist-info/entry_points.txt
hi_hamsunwoo-0.8.0.dist-info/top_level.txt
hi_hamsunwoo-0.8.0.dist-info/RECORD
