Metadata-Version: 2.1
Name: hi_hamsunwoo
Version: 0.8.0
Summary: Default template for PDM package
Author-email: sunwoo <summerham22@gmail.com>
License: MIT
Requires-Python: ==3.9.*
